collective.pivot-1.0a6-py2.7-nspkg.pth
collective/pivot/__init__.py
collective/pivot/config.py
collective/pivot/configure.zcml
collective/pivot/interfaces.py
collective/pivot/permissions.zcml
collective/pivot/setuphandlers.py
collective/pivot/testing.py
collective/pivot/utils.py
collective/pivot/vocabularies.py
collective/pivot/browser/__init__.py
collective/pivot/browser/configure.zcml
collective/pivot/browser/controlpanel.py
collective/pivot/browser/static/.gitkeep
collective/pivot/browser/static/pivot/layers-2x.png
collective/pivot/browser/static/pivot/layers.png
collective/pivot/browser/static/pivot/marker-icon.png
collective/pivot/browser/static/pivot/pivot.js
collective/pivot/browser/static/pivot/pivot.js.LICENSE.txt
collective/pivot/contents/__init__.py
collective/pivot/contents/configure.zcml
collective/pivot/contents/family/__init__.py
collective/pivot/contents/family/configure.zcml
collective/pivot/contents/family/content.py
collective/pivot/contents/family/endpoint.py
collective/pivot/contents/family/view.pt
collective/pivot/contents/family/view.py
collective/pivot/locales/README.rst
collective/pivot/locales/__init__.py
collective/pivot/locales/collective.pivot.pot
collective/pivot/locales/update.py
collective/pivot/locales/update.sh
collective/pivot/locales/en/LC_MESSAGES/collective.pivot.po
collective/pivot/locales/fr/LC_MESSAGES/collective.pivot.po
collective/pivot/profiles/content/metadata.xml
collective/pivot/profiles/default/browserlayer.xml
collective/pivot/profiles/default/controlpanel.xml
collective/pivot/profiles/default/metadata.xml
collective/pivot/profiles/default/registry.xml
collective/pivot/profiles/default/rolemap.xml
collective/pivot/profiles/default/types.xml
collective/pivot/profiles/default/types/collective.pivot.Family.xml
collective/pivot/profiles/uninstall/browserlayer.xml
collective/pivot/react/package-lock.json
collective/pivot/react/package.json
collective/pivot/react/post-build.sh
collective.pivot-1.0a6.dist-info/DESCRIPTION.rst
collective.pivot-1.0a6.dist-info/METADATA
collective.pivot-1.0a6.dist-info/RECORD
collective.pivot-1.0a6.dist-info/WHEEL
collective.pivot-1.0a6.dist-info/entry_points.txt
collective.pivot-1.0a6.dist-info/metadata.json
collective.pivot-1.0a6.dist-info/namespace_packages.txt
collective.pivot-1.0a6.dist-info/top_level.txt
