Metadata-Version: 2.0
Name: collective.pivot
Version: 1.0a6
Summary: Display CGT Pivot informations
Home-page: https://github.com/IMIO/collective.pivot
Author: Christophe Boulanger
Author-email: christophe.boulanger@imio.be
License: GPL version 2
Project-URL: Source, https://github.com/IMIO/collective.pivot
Project-URL: Tracker, https://github.com/IMIO/collective.pivot/issues
Project-URL: PyPI, https://pypi.python.org/pypi/collective.pivot
Keywords: Python Plone CMS
Platform: UNKNOWN
Classifier: Environment :: Web Environment
Classifier: Framework :: Plone
Classifier: Framework :: Plone :: Addon
Classifier: Framework :: Plone :: 4.3
Classifier: Framework :: Plone :: 5.2
Classifier: Programming Language :: Python
Classifier: Programming Language :: Python :: 2.7
Classifier: Programming Language :: Python :: 3.8
Classifier: Operating System :: OS Independent
Classifier: License :: OSI Approved :: GNU General Public License v2 (GPLv2)
Provides-Extra: test
Requires-Dist: setuptools
Requires-Dist: z3c.jbot
Requires-Dist: Products.GenericSetup (>=1.8.2)
Requires-Dist: plone.api (>=1.8.4)
Requires-Dist: plone.restapi
Requires-Dist: plone.app.dexterity
Requires-Dist: plone.app.relationfield
Requires-Dist: plone.app.lockingbehavior
Requires-Dist: plone.schema
Requires-Dist: requests
Provides-Extra: test
Requires-Dist: plone.app.testing; extra == 'test'
Requires-Dist: plone.testing (>=5.0.0); extra == 'test'
Requires-Dist: plone.app.robotframework[debug]; extra == 'test'
Requires-Dist: requests-mock; extra == 'test'
